lib_excel.py
lib_excel_package.py
setup.py
lib_excel.egg-info/PKG-INFO
lib_excel.egg-info/SOURCES.txt
lib_excel.egg-info/dependency_links.txt
lib_excel.egg-info/top_level.txt