Metadata-Version: 1.0
Name: lib-excel
Version: 1.2
Summary: General purpose utility functions
Home-page: UNKNOWN
Author: Albert Benzimra
Author-email: benzimra@comcast.net
License: UNKNOWN
Platform: UNKNOWN
